tastypie_extras/__init__.py
tastypie_extras/authentication.py
tastypie_extras/paginator.py
tastypie_extras/resource.py
tastypie_extras/resources.py
tastypie_extras/serializers/__init__.py
tastypie_extras/serializers/csv.py
django_tastypie_extras-0.4b4.dist-info/LICENSE
django_tastypie_extras-0.4b4.dist-info/METADATA
django_tastypie_extras-0.4b4.dist-info/WHEEL
django_tastypie_extras-0.4b4.dist-info/top_level.txt
django_tastypie_extras-0.4b4.dist-info/RECORD
